{"stats":{"minecraft:mined":{"testmod:md_ore":1},"minecraft:used":{"minecraft:sandstone":54,"testmod:md_ore":38,"minecraft:ancient_debris":10,"testmod:mod_block":39,"testmod:fabric_pickaxe":1},"minecraft:custom":{"minecraft:jump":56,"minecraft:time_since_rest":3416,"minecraft:crouch_one_cm":3885,"minecraft:play_one_minute":3416,"minecraft:leave_game":1,"minecraft:sprint_one_cm":3187,"minecraft:time_since_death":3416,"minecraft:walk_one_cm":13569,"minecraft:sneak_time":555,"minecraft:fly_one_cm":17489}},"DataVersion":2586}